{
  "date": "2026-06-23",
  "generated_at": "2026-06-23 06:31 KST",
  "pdf_date": "20260623",
  "pdf_count": 17,
  "is_fallback": false,
  "categories": {
    "경제일반": [
      {
        "title": "2030세대 '생존결혼' 확산…6년 만에 혼인건수 최다",
        "summary": "집값·전월세 상승과 생활비 부담으로 혼자 버티기 어려워진 2030세대가 자산 형성을 위해 결혼을 서두르는 '생존결혼' 현상이 확산되고 있다. 2026년 1분기 혼인건수는 전년 동기 대비 6.1% 증가한 6만2309건으로, 2018년 이후 6년 만에 연간 25만 건을 넘길 전망이다. 웨딩홀 예약난과 공공예식 수요 급증, 신혼부부 주거정책 등이 결혼을 앞당기는 요인으로 꼽힌다.",
        "keywords": [
          "생존결혼",
          "혼인건수",
          "2030세대",
          "집값",
          "신혼부부"
        ]
      },
      {
        "title": "20대 취업 시계 늦춰지고 30대 노동시장 참여 본격화",
        "summary": "20~24세 청년의 취업 비중이 2009년 45%에서 2024년 31%로 14%포인트 하락한 반면, 25~29세와 30~34세 취업 비중은 크게 상승했다. 대학 졸업 후 스펙 쌓기를 거쳐 30대 전후에 노동시장에 진입하는 것이 일반화됐으며, 20대 남성 '니트족' 비율도 증가하는 추세다.",
        "keywords": [
          "청년취업",
          "니트족",
          "취업시계",
          "노동시장",
          "20대"
        ]
      },
      {
        "title": "상호금융권 올해 예금 15조원 이탈…세제혜택 축소·증시 호황 영향",
        "summary": "올해 새마을금고·신협 등 상호금융권에서 예금이 15조2301억원 빠져나갔다. 증시 강세로 자금이 주식으로 이동한 '머니무브'와 함께 올해부터 상호금융 조합원의 예탁금 비과세 기준이 축소되면서 세제 혜택이 사라진 것이 주요 원인이다. 부동산 PF 부실로 신뢰도가 하락한 것도 악재로 작용했다.",
        "keywords": [
          "상호금융",
          "새마을금고",
          "신협",
          "예금이탈",
          "비과세혜택"
        ]
      }
    ],
    "산업/기업": [
      {
        "title": "SK하이닉스, 삼성전자 제치고 코스피 시총 1위 등극…26년 만의 왕좌 교체",
        "summary": "SK하이닉스가 22일 5.61% 상승한 291만9000원에 마감하며 시가총액 2080조3782억원을 기록, 삼성전자(보통주 기준 2066조6594억원)를 처음으로 추월해 코스피 시총 1위에 올랐다. 2003년 주가가 135원까지 떨어졌던 동전주가 AI 시대 HBM 반도체 시장을 선점하며 26년 만에 대장주 자리를 차지했다. 미국 ADR 상장 추진으로 추가 밸류에이션 재평가가 기대된다.",
        "keywords": [
          "SK하이닉스",
          "삼성전자",
          "시총1위",
          "HBM",
          "코스피"
        ]
      },
      {
        "title": "탄약 만들던 풍산, 드론 강자로 부상",
        "summary": "방위산업 스타트업 붐이 일면서 탄약 전문기업 풍산이 드론 분야 강자로 떠오르고 있다. 우크라이나 전쟁과 중동 분쟁으로 차세대 무기체계 수요가 늘며 올해 방위산업 기술 스타트업에 123억달러 넘는 벤처 자금이 유입됐다.",
        "keywords": [
          "풍산",
          "방산",
          "드론",
          "스타트업",
          "무기체계"
        ]
      },
      {
        "title": "AI 마케팅 기업, 코스닥 입성 도전",
        "summary": "AI 기반 마케팅 자동화 솔루션 기업 매거진과 스마트 병원 플랫폼 기업 레몬헬스케어가 각자의 인공지능 기술 고도화와 재무건전성을 앞세워 코스닥 시장 육성에 전념하고 있다.",
        "keywords": [
          "AI마케팅",
          "코스닥",
          "스타트업",
          "IPO",
          "인공지능"
        ]
      }
    ],
    "국제": [
      {
        "title": "앨런 그린스펀 전 Fed 의장 별세…향년 100세",
        "summary": "19년간 미국 연방준비제도를 이끈 앨런 그린스펀 전 의장이 파킨슨병 합병증으로 별세했다. 향년 100세. 1987년 8월부터 2006년 1월까지 18년5개월간 재직하며 경기 호황기를 이끌었으나 자산시장 거품을 키워 세계 금융위기를 불렀다는 평가도 받는다.",
        "keywords": [
          "그린스펀",
          "Fed",
          "연방준비제도",
          "별세",
          "중앙은행"
        ]
      }
    ],
    "정치/정책": [
      {
        "title": "이재명 정부 부동산 정책 1년…매매·전·월세 '트리플 상승' 딜레마",
        "summary": "이재명 정부가 출범 1년간 담보대출 상한, 다주택자 규제, 토지거래허가구역 확대 등 수요 억제 중심 정책을 펼쳤으나 서울 아파트 매매가 11%, 전·월세 6~7% 상승하는 등 시장이 반대 방향으로 움직이고 있다. 공급 위축과 전월세 물량 감소가 겹치며 무주택 서민 부담이 가중되고, 다음달 세제 규제 강화도 예고돼 있다.",
        "keywords": [
          "부동산정책",
          "이재명정부",
          "트리플상승",
          "수요억제",
          "공급위축"
        ]
      },
      {
        "title": "소상공인·중소기업까지 단체교섭 쓰나미 오나",
        "summary": "노조의 단체교섭 대상이 소상공인과 중소기업까지 확대될 가능성이 제기되며 경영계가 우려를 표하고 있다.",
        "keywords": [
          "단체교섭",
          "소상공인",
          "중소기업",
          "노조",
          "노동정책"
        ]
      }
    ],
    "금융/증권": [
      {
        "title": "SK하이닉스 목표주가 430만원 등장…반도체 수출 급증에 투자심리 고조",
        "summary": "6월 1~20일 반도체 수출이 전년 동기 대비 188.4% 급증하며 전체 수출의 40% 이상을 차지한 가운데 증권사들이 반도체주 목표주가를 잇따라 상향 조정했다. 한화증권은 SK하이닉스 목표주가를 430만원으로 제시했고, iM증권도 삼성전자·SK하이닉스 목표주가를 각각 20·26% 높였다. 24일 예정된 마이크론 실적 발표가 추가 상승의 촉매가 될 것으로 기대된다.",
        "keywords": [
          "SK하이닉스",
          "목표주가",
          "반도체수출",
          "마이크론",
          "코스피"
        ]
      },
      {
        "title": "'멜트업 장세' 진단…AI 수혜주 포지션 구축 조언",
        "summary": "왕리자산운용 최홍석 ETF솔루션 본부장은 현재 증시를 과열된 '멜트업' 장세로 진단하면서도 '제네시스 미션' 관련 AI 인프라 수혜주를 주목해야 한다고 조언했다. 투자정보 전문 AI인 제미나이AI가 관련 종목을 분석 중이다.",
        "keywords": [
          "멜트업",
          "AI수혜주",
          "ETF",
          "포지션구축",
          "증시"
        ]
      }
    ],
    "부동산": [
      {
        "title": "기로에 선 부동산 정책…수요 억제만으론 한계, 공급 확대 병행 필요",
        "summary": "이재명 정부의 1년간 부동산 정책 성적표는 서울 아파트 매매·전세·월세 동반 상승으로 나타났다. 공사비 상승과 PF 위기, 재건축·재개발 지연으로 공급 부족이 누적된 상황에서 수요 억제 일변도 정책의 한계가 드러나고 있으며, 전문가들은 민간 주택 공급을 파트너로 활용하는 방향으로 정책 전환이 필요하다고 제언했다.",
        "keywords": [
          "부동산정책",
          "공급부족",
          "전세",
          "수요억제",
          "주택시장"
        ]
      }
    ]
  }
}