{
  "date": "2026-06-30",
  "generated_at": "2026-06-30 22:27 KST",
  "pdf_date": "20260630",
  "pdf_count": 15,
  "is_fallback": false,
  "sectors": {
    "반도체/AI": {
      "flow": "정부 주도의 호남 반도체·AI 메가프로젝트가 공식화되면서, 삼성·SK의 800조원 투자로 반도체 팹 4기가 호남에 들어서고 전국 7곳에 18.4GW 규모 AI 데이터센터가 구축된다. 여기서 주목할 점은 이번 호남 클러스터가 2019년 용인 클러스터의 '보텀업' 방식과 달리 청와대 주도 '톱다운' 방식으로 결정됐다는 점으로, 속도는 빠르지만 민간 자율성과 지속성에 대한 우려가 제기된다. 전문가들은 대규모 투자 발표와 별개로 전력·용수·인력 등 3대 인프라의 체계적 선행 조성 없이는 클러스터 실제 가동이 지연될 수 있다고 경고하며, 하드웨어 투자 못지않게 소프트 인프라 확충이 성패를 가를 것임을 시사한다.",
      "articles": [
        {
          "title": "3대 메가프로젝트: 호남 반도체·AI데이터센터·로봇 투자",
          "key_sentence": "삼성·SK 800조원 투자, 호남 반도체 팹 4기·전국 AI데이터센터 7곳 건설"
        },
        {
          "title": "SK·GS 등 7곳, AI 데이터센터 건설",
          "key_sentence": "삼성SDS·네이버·GS 등, 전국 7곳 18.4GW 규모 AI 데이터센터 구축"
        },
        {
          "title": "제반 인프라 조성 선행 돼야",
          "key_sentence": "반도체 클러스터 가동, 전력·용수·인력 3대 인프라 체계적 지원 필수"
        },
        {
          "title": "용인·호남 클러스터 전략 차이",
          "key_sentence": "용인 보텀업 vs 호남 청와대 주도 톱다운 방식, 투자 결정 구조 대비"
        }
      ]
    },
    "금융/증권": {
      "flow": "100억원 이상 예탁금 보유 투자자 수가 1년 새 2195명에서 4510명으로 105% 급증한 것은 국내 주식시장에서 자산 집중이 빠르게 심화되고 있음을 보여준다. 이는 AI·반도체 등 대형 테마주 중심의 강세장이 고자산 투자자에게 불균형적으로 유리하게 작용한 결과로 해석되며, 개인 투자자 저변 확대보다 '슈퍼 주식부자' 계층의 확장이 두드러진 시장 구조를 시사한다.",
      "articles": [
        {
          "title": "100억원 이상 주식부자 1년새 2배 늘었다",
          "key_sentence": "예탁금 100억원 이상 투자자 4510명, 전년 2195명 대비 105% 급증"
        }
      ]
    },
    "유통/소비": {
      "flow": "K뷰티가 단순 화장품 제품 수출을 넘어 편집숍·플랫폼 형태로 미국·유럽 시장에 진출하고 있다. 실리콘투·오프뷰티 등이 현지에서 K뷰티 편집숍 브랜드를 직접 운영하며 유통 구조 자체를 수출하는 전략으로 전환한 것은, 제품 경쟁력을 넘어 브랜드·채널 경쟁력까지 글로벌화하는 단계에 접어들었음을 의미하며 K뷰티 수출의 질적 고도화를 시사한다.",
      "articles": [
        {
          "title": "K뷰티 단순 화장품 판매 넘어 플랫폼 수출",
          "key_sentence": "실리콘투·오프뷰티 등 K뷰티 편집숍 브랜드, 미국·유럽 직접 진출 확대"
        }
      ]
    },
    "부동산/건설": {
      "flow": "2026년 상반기 한경주거문화대상에서 경기광주 롯데캐슬·도안자이 등 22개 상품이 수상했다. 대형 건설사 브랜드 단지가 주거문화 트렌드를 주도하고 있음을 반영하며, 수요자들의 주거 품질과 브랜드 신뢰도에 대한 선호가 여전히 높다는 시장 분위기를 확인할 수 있다.",
      "articles": [
        {
          "title": "2026년 상반기 한경주거문화대상",
          "key_sentence": "경기광주 롯데캐슬·도안자이 등 22개 상품 한경주거문화대상 수상"
        }
      ]
    },
    "정책/정치": {
      "flow": "민주당 내부에서는 당권 경쟁을 둘러싸고 정청래의 친노 정통성 논란이 불거지며 친노·친문 계파 갈등이 격화되고 있다. 동시에 국민의힘은 6·3 투표용지 사건과 관련해 선관위 특검을 당론으로 공식 채택하며 야권 압박 수위를 높이고 있다. 두 사안은 각각 여야 내부 결속과 대외 공세로 분리되지만, 하반기 정국 주도권을 둘러싼 여야 간 전선이 사법·계파 갈등 축으로 동시에 형성되고 있음을 보여준다.",
      "articles": [
        {
          "title": "정청래 \"허위사실\" 반발…당내 친노·친문 갈등 심화",
          "key_sentence": "민주당 당권 경쟁, 정청래 친노 정통성 논란으로 계파 갈등 격화"
        },
        {
          "title": "여당, 선관위 특검 추진 당론으로",
          "key_sentence": "국민의힘, 6·3 투표용지 사건 관련 선관위 특검을 공식 당론 채택"
        }
      ]
    }
  }
}