{
  "updated_at": "2026-06-30 22:40 KST",
  "exchange_rate": {
    "usd_krw": 1551.0,
    "change": 15.76,
    "change_pct": 1.0266
  },
  "indices": {
    "sp500": {
      "value": 7442.1299,
      "change": 1.6997,
      "change_pct": 0.0228
    },
    "nasdaq": {
      "value": 25890.4004,
      "change": 70.2598,
      "change_pct": 0.2721
    },
    "dow": {
      "value": 52091.9805,
      "change": -90.7578,
      "change_pct": -0.1739
    },
    "kospi": {
      "value": 8476.4805,
      "change": 81.8301,
      "change_pct": 0.9748
    },
    "kosdaq": {
      "value": 916.18,
      "change": -4.39,
      "change_pct": -0.4769
    }
  },
  "commodities": {
    "gold": {
      "price": 4038.8,
      "change": 16.5,
      "change_pct": 0.4102
    },
    "silver": {
      "price": 59.53,
      "change": 1.355,
      "change_pct": 2.3292
    },
    "crude_oil": {
      "price": 71.17,
      "change": 0.42,
      "change_pct": 0.5936
    },
    "natural_gas": {
      "price": 3.257,
      "change": 0.076,
      "change_pct": 2.3892
    }
  },
  "vix": {
    "value": 17.69,
    "change": 0.04,
    "change_pct": 0.2266
  },
  "fear_greed": {
    "value": 78,
    "label": "극도의 탐욕"
  },
  "portfolio": [
    {
      "ticker": "010140.KS",
      "name": "삼성중공업",
      "currency": "KRW",
      "price": 23300.0,
      "change": -1150.0,
      "change_pct": -4.7035,
      "shares": 165,
      "avg_price": 30156,
      "value": 3844500.0,
      "pl": -1131240.0,
      "pl_pct": -22.7351
    },
    {
      "ticker": "189300.KS",
      "name": "인텔리안테크",
      "currency": "KRW",
      "price": 75900.0,
      "change": 5600.0,
      "change_pct": 7.9659,
      "shares": 25,
      "avg_price": 168500,
      "value": 1897500.0,
      "pl": -2315000.0,
      "pl_pct": -54.9555
    },
    {
      "ticker": "107640.KS",
      "name": "한중엔시에스",
      "currency": "KRW",
      "price": 36250.0,
      "change": 4900.0,
      "change_pct": 15.63,
      "shares": 68,
      "avg_price": 58800,
      "value": 2465000.0,
      "pl": -1533400.0,
      "pl_pct": -38.3503
    },
    {
      "ticker": "171090.KS",
      "name": "선익시스템",
      "currency": "KRW",
      "price": 59300.0,
      "change": 4500.0,
      "change_pct": 8.2117,
      "shares": 45,
      "avg_price": 91000,
      "value": 2668500.0,
      "pl": -1426500.0,
      "pl_pct": -34.8352
    },
    {
      "ticker": "000720.KS",
      "name": "현대건설",
      "currency": "KRW",
      "price": 114200.0,
      "change": -1900.0,
      "change_pct": -1.6365,
      "shares": 25,
      "avg_price": 160800,
      "value": 2855000.0,
      "pl": -1165000.0,
      "pl_pct": -28.9801
    },
    {
      "ticker": "0004G0.KS",
      "name": "1Q 미국배당TOP30",
      "currency": "KRW",
      "price": 9695.0,
      "change": 15.0,
      "change_pct": 0.155,
      "shares": 63,
      "avg_price": 9385,
      "value": 610785.0,
      "pl": 19530.0,
      "pl_pct": 3.3031
    },
    {
      "ticker": "458730.KS",
      "name": "TIGER 미국배당다우존스",
      "currency": "KRW",
      "price": 15735.0,
      "change": -15.0,
      "change_pct": -0.0952,
      "shares": 52,
      "avg_price": 15198,
      "value": 818220.0,
      "pl": 27924.0,
      "pl_pct": 3.5334
    },
    {
      "ticker": "SPYM",
      "name": "SPDR Portfolio S&P 500",
      "currency": "USD",
      "price": 87.25,
      "change": 0.07,
      "change_pct": 0.0746,
      "shares": 17,
      "avg_price": 82.66,
      "value": 1483.16,
      "pl": 77.95,
      "pl_pct": 5.5468
    },
    {
      "ticker": "QBTS",
      "name": "디웨이브퀀텀",
      "currency": "USD",
      "price": 23.61,
      "change": -0.22,
      "change_pct": -0.9232,
      "shares": 65,
      "avg_price": 29.9,
      "value": 1534.65,
      "pl": -408.85,
      "pl_pct": -21.0368
    }
  ],
  "briefing": "6월 30일 마감 기준, 글로벌 시장은 분화된 흐름 속에 한 달을 마무리했습니다. 원/달러 환율이 1,551원(+1.03%)으로 재차 올라서며 원화 약세가 지속되고 있어, 수출주에는 우호적이나 수입 원가 부담 가중에 유의해야 합니다. 금은 4,038달러(+0.41%), 은은 59.53달러(+2.33%)로 귀금속 전반이 강세를 이어갔고, 천연가스도 +2.39% 급등해 에너지 섹터 전반에 상승 압력이 형성됐습니다. WTI 원유는 71.17달러로 소폭 반등하며 안정적 흐름을 유지하고 있습니다. VIX 17.69는 변동성 우려가 낮은 수준임을 시사하지만, 공포탐욕 지수 78의 '극도의 탐욕' 구간은 단기 과열 경계 신호로 읽힙니다. 월말 포지션 정리 이후 7월 초 시장 방향성 재확인이 중요한 변수가 될 전망입니다.",
  "section_comments": {
    "kr_indices": "KOSPI는 8,476선까지 올라서며 강세를 보인 반면, KOSDAQ은 0.48% 하락해 대형주와 중소형주 간 뚜렷한 온도 차가 나타났다. 포트폴리오 내 한중엔시에스(+15.63%), 선익시스템(+8.21%), 인텔리안테크(+7.97%) 등 테마 중소형주가 급등한 점은 고무적이나, 삼성중공업(-4.70%)과 현대건설(-1.64%) 등 대형 산업재가 동반 조정된 흐름도 주목된다.",
    "us_indices": "미국 3대 지수는 혼조세로 마감해 뚜렷한 방향성을 확인하기 어려운 장이었다. 나스닥이 기술주 매수세에 힘입어 소폭 상승하며 25,890선을 유지한 반면, 다우존스는 경기민감주 중심의 차익 실현으로 소폭 밀렸다. 공포탐욕 지수 78(극도의 탐욕) 수준에서 신규 매수보다는 관망 심리가 교차하는 구간으로 판단된다."
  }
}